dc_ore_packager/DCOREPackager.py
dc_ore_packager/__init__.py
dc_ore_packager-0.0.3.dist-info/LICENSE
dc_ore_packager-0.0.3.dist-info/METADATA
dc_ore_packager-0.0.3.dist-info/WHEEL
dc_ore_packager-0.0.3.dist-info/top_level.txt
dc_ore_packager-0.0.3.dist-info/RECORD
