Metadata-Version: 2.1
Name: dc-ore-packager
Version: 0.0.3
Summary: A simple DublinCore/ORE SimpleArchive Packager
Home-page: https://github.com/BrunoNZ/dc-ore-packager
Author: Bruno Nocera Zanette
Author-email: brunonzanette@gmail.com
License: UNKNOWN
Platform: UNKNOWN
Classifier: Programming Language :: Python :: 3
Classifier: License :: OSI Approved :: MIT License
Classifier: Operating System :: OS Independent
Requires-Python: >=3.6
